odoo8_addon_crm_phonecall_summary_predefined-8.0.1.0.0.99.dev30-py2.7-nspkg.pth
odoo8_addon_crm_phonecall_summary_predefined-8.0.1.0.0.99.dev30.dist-info/METADATA
odoo8_addon_crm_phonecall_summary_predefined-8.0.1.0.0.99.dev30.dist-info/RECORD
odoo8_addon_crm_phonecall_summary_predefined-8.0.1.0.0.99.dev30.dist-info/WHEEL
odoo8_addon_crm_phonecall_summary_predefined-8.0.1.0.0.99.dev30.dist-info/namespace_packages.txt
odoo8_addon_crm_phonecall_summary_predefined-8.0.1.0.0.99.dev30.dist-info/top_level.txt
odoo_addons/crm_phonecall_summary_predefined/README.rst
odoo_addons/crm_phonecall_summary_predefined/__init__.py
odoo_addons/crm_phonecall_summary_predefined/__openerp__.py
odoo_addons/crm_phonecall_summary_predefined/i18n/am.po
odoo_addons/crm_phonecall_summary_predefined/i18n/ar.po
odoo_addons/crm_phonecall_summary_predefined/i18n/bg.po
odoo_addons/crm_phonecall_summary_predefined/i18n/bs.po
odoo_addons/crm_phonecall_summary_predefined/i18n/ca.po
odoo_addons/crm_phonecall_summary_predefined/i18n/ca_ES.po
odoo_addons/crm_phonecall_summary_predefined/i18n/crm_phonecall_summary_predefined.pot
odoo_addons/crm_phonecall_summary_predefined/i18n/cs.po
odoo_addons/crm_phonecall_summary_predefined/i18n/da.po
odoo_addons/crm_phonecall_summary_predefined/i18n/da_DK.po
odoo_addons/crm_phonecall_summary_predefined/i18n/de.po
odoo_addons/crm_phonecall_summary_predefined/i18n/el_GR.po
odoo_addons/crm_phonecall_summary_predefined/i18n/en_GB.po
odoo_addons/crm_phonecall_summary_predefined/i18n/es.po
odoo_addons/crm_phonecall_summary_predefined/i18n/es_AR.po
odoo_addons/crm_phonecall_summary_predefined/i18n/es_CL.po
odoo_addons/crm_phonecall_summary_predefined/i18n/es_CO.po
odoo_addons/crm_phonecall_summary_predefined/i18n/es_CR.po
odoo_addons/crm_phonecall_summary_predefined/i18n/es_DO.po
odoo_addons/crm_phonecall_summary_predefined/i18n/es_EC.po
odoo_addons/crm_phonecall_summary_predefined/i18n/es_ES.po
odoo_addons/crm_phonecall_summary_predefined/i18n/es_MX.po
odoo_addons/crm_phonecall_summary_predefined/i18n/es_PE.po
odoo_addons/crm_phonecall_summary_predefined/i18n/es_PY.po
odoo_addons/crm_phonecall_summary_predefined/i18n/es_VE.po
odoo_addons/crm_phonecall_summary_predefined/i18n/et.po
odoo_addons/crm_phonecall_summary_predefined/i18n/eu.po
odoo_addons/crm_phonecall_summary_predefined/i18n/fa.po
odoo_addons/crm_phonecall_summary_predefined/i18n/fi.po
